[
  {
    "link_it": "https://github.com/lmbstudiocontact/lv_img_3500_it_1/raw/main/doctor_lv_img_3500_it.json",
    "id_item": "doctor_lv_img_3500_it",
    "id_album": "570943488",
    "english": "doctor",
    "list_mean": [
      "bác sĩ y khoa",
      "tiến sĩ",
      "(hàng hải), (từ lóng) người đầu bếp, anh nuôi (trên tàu)",
      "bộ phận điều chỉnh (ở máy)",
      "ruồi già (để câu cá)",
      "chữa bệnh cho (ai); trị (bệnh)",
      "thiến, hoạn (đối với súc vật)",
      "làm giả; giả mạo",
      "( to doctor something with something ) thêm cái gì có hại vào đồ ăn thức uống",
      "làm bác sĩ y khoa"
    ],
    "cau_en": "to doctor the evidence , the accounts , a report",
    "cau_vn": "sửa bằng chứng, sổ sách kế toán, bản báo cáo (để đánh lừa)",
    "hash_code_list_mean": "1571207373",
    "list_img": [
      {
        "link_thumb": "https://live.staticflickr.com/65535/51809312071_e1c373c9c5_n.jpg",
        "link_img": "https://live.staticflickr.com/65535/51809312071_f51af48471_o.png",
        "id_image": "doctor_307942"
      },
      {
        "link_thumb": "https://live.staticflickr.com/65535/51810048645_2a6495e015_n.jpg",
        "link_img": "https://live.staticflickr.com/65535/51810048645_068e5e6fa3_o.png",
        "id_image": "doctor_771338"
      },
      {
        "link_thumb": "https://live.staticflickr.com/65535/51809666879_986263e315_n.jpg",
        "link_img": "https://live.staticflickr.com/65535/51809666879_7cdc69b554_o.png",
        "id_image": "doctor_773383"
      }
    ],
    "hash_code_list_img": "-1423195015"
  },
  {
    "link_it": "https://github.com/lmbstudiocontact/lv_img_3500_it_1/raw/main/formula_lv_img_3500_it.json",
    "id_item": "formula_lv_img_3500_it",
    "id_album": "570943488",
    "english": "formula",
    "list_mean": [
      "thể thức; cách thức",
      "công thức",
      "kế hoạch; phương pháp",
      "sự phân loại xe đua theo kích thước, công suất...",
      "sữa bột nhân tạo cho trẻ em"
    ],
    "cau_en": "managers and workers are still working out a peace formula",
    "cau_vn": "giới chủ và công nhân vẫn đang hoạch định một kế hoạch hoà bình",
    "hash_code_list_mean": "-1180865283",
    "list_img": [
      {
        "link_thumb": "https://live.staticflickr.com/65535/51809429528_fb3606bbb7_n.jpg",
        "link_img": "https://live.staticflickr.com/65535/51809429528_6503e6d6b9_o.png",
        "id_image": "formula_1702303"
      },
      {
        "link_thumb": "https://live.staticflickr.com/65535/51809669269_59a5ebc8be_n.jpg",
        "link_img": "https://live.staticflickr.com/65535/51809669269_6ae24e03da_o.png",
        "id_image": "formula_3830342"
      },
      {
        "link_thumb": "https://live.staticflickr.com/65535/51810051220_527ffaf0c2_n.jpg",
        "link_img": "https://live.staticflickr.com/65535/51810051220_4c97b08641_o.png",
        "id_image": "formula_407418"
      },
      {
        "link_thumb": "https://live.staticflickr.com/65535/51808358777_a19c8cae0f_n.jpg",
        "link_img": "https://live.staticflickr.com/65535/51808358777_08059fa611_o.png",
        "id_image": "formula_843193"
      }
    ],
    "hash_code_list_img": "1663715660"
  },
  {
    "link_it": "https://github.com/lmbstudiocontact/lv_img_3500_it_3/raw/main/shampoo_lv_img_3500_it.json",
    "id_item": "shampoo_lv_img_3500_it",
    "id_album": "570943488",
    "english": "shampoo",
    "list_mean": [
      "săng-poang; dầu gội đầu",
      "dầu giặt thảm, dầu rửa xe",
      "sự gội đầu, hành động gội đầu; sự lau chùi",
      "gội đầu",
      "(từ hiếm,nghĩa hiếm) tẩm quất, xoa bóp (sau khi tắm nước nóng)"
    ],
    "cau_en": "To give somebody a shampoo",
    "cau_vn": "Gội đầu cho ai bằng dầu gội đầu",
    "hash_code_list_mean": "1637607495",
    "list_img": [
      {
        "link_thumb": "https://live.staticflickr.com/65535/51809462153_ab15ca5ecf_n.jpg",
        "link_img": "https://live.staticflickr.com/65535/51809462153_6480827b29_o.png",
        "id_image": "shampoo_4157623"
      },
      {
        "link_thumb": "https://live.staticflickr.com/65535/51808392352_883f2b2837_n.jpg",
        "link_img": "https://live.staticflickr.com/65535/51808392352_6e2ed62ee8_o.png",
        "id_image": "shampoo_4310660"
      },
      {
        "link_thumb": "https://live.staticflickr.com/65535/51809462078_db6fc71532_n.jpg",
        "link_img": "https://live.staticflickr.com/65535/51809462078_c0551de0a9_o.png",
        "id_image": "shampoo_6075408"
      }
    ],
    "hash_code_list_img": "1896860717"
  },
  {
    "link_it": "https://github.com/lmbstudiocontact/lv_img_3500_it_2/raw/main/release_lv_img_3500_it.json",
    "id_item": "release_lv_img_3500_it",
    "id_album": "570943488",
    "english": "release",
    "list_mean": [
      "sự giải thoát, sự thoát khỏi (điều lo lắng, sầu muộn, bệnh tật...)",
      "sự thả, sự phóng thích",
      "sự phát hành (cuốn sách, bản tin); sự đưa ra bán (một loại ô tô mới...)",
      "giấy biên lai, giấy biên nhận",
      "(pháp lý) sự nhượng lại; giấy nhượng lại",
      "(vật lý) sự tách ra, sự nhả ra, sự giải phóng",
      "(kỹ thuật) cái ngắt điện",
      "(kỹ thuật) sự cắt, sự tháo ra",
      "(quân sự) sự ném, sự thả, sự cắt (bom); sự mở (dù)",
      "sự giải ngũ, sự phục viên",
      "(hoá học) sự bay ra, sự thoát ra (hơi)",
      "làm nhẹ, làm bớt, làm thoát khỏi (đau đớn, sầu muộn, bệnh tật...)",
      "tha, thả, phóng thích",
      "miễn, tha (nợ...), giải thoát",
      "phát hành (cuốn phim, bản tin...); đăng (tin); đưa ra bán (một loại ô tô mới...)",
      "(pháp lý) nhường, nhượng",
      "(vật lý) cắt dòng",
      "(kỹ thuật) nhả khớp, tháo ra, tách ra, cắt mạch",
      "(quân sự) ném, thả, cắt (bom); mở (dù)",
      "(quân sự) cho giải ngũ, cho phục viên",
      "(hoá học) làm bay ra, làm thoát ra (hơi)"
    ],
    "cau_en": "to release someone from his promise",
    "cau_vn": "giải ước cho ai",
    "hash_code_list_mean": "812144667",
    "list_img": [
      {
        "link_thumb": "https://live.staticflickr.com/65535/51809442268_b6a50024e0_n.jpg",
        "link_img": "https://live.staticflickr.com/65535/51809442268_ed54ffaff0_o.png",
        "id_image": "release_2040729"
      },
      {
        "link_thumb": "https://live.staticflickr.com/65535/51808371902_46c416ec51_n.jpg",
        "link_img": "https://live.staticflickr.com/65535/51808371902_b14e243843_o.png",
        "id_image": "release_2621061"
      },
      {
        "link_thumb": "https://live.staticflickr.com/65535/51809327116_4d78601636_n.jpg",
        "link_img": "https://live.staticflickr.com/65535/51809327116_3b4803022b_o.png",
        "id_image": "release_2621067"
      },
      {
        "link_thumb": "https://live.staticflickr.com/65535/51809442148_b2e44fb723_n.jpg",
        "link_img": "https://live.staticflickr.com/65535/51809442148_ed7955abb8_o.png",
        "id_image": "release_4382599"
      },
      {
        "link_thumb": "https://live.staticflickr.com/65535/51809442103_b2728b45aa_n.jpg",
        "link_img": "https://live.staticflickr.com/65535/51809442103_07c910488d_o.png",
        "id_image": "release_4458940"
      }
    ],
    "hash_code_list_img": "1927588071"
  },
  {
    "link_it": "https://github.com/lmbstudiocontact/lv_img_3500_it_2/raw/main/octagon_lv_img_3500_it.json",
    "id_item": "octagon_lv_img_3500_it",
    "id_album": "570943488",
    "english": "octagon",
    "list_mean": [
      "(toán học) hình bát giác; hình tám cạnh"
    ],
    "cau_en": "that box is octagon",
    "cau_vn": "cái hộp đó hình bát giác",
    "hash_code_list_mean": "-1406404056",
    "list_img": [
      {
        "link_thumb": "https://live.staticflickr.com/65535/51809703804_7cf9ea9b50_n.jpg",
        "link_img": "https://live.staticflickr.com/65535/51809703804_4cb6f07229_o.png",
        "id_image": "octagon_3810200"
      },
      {
        "link_thumb": "https://live.staticflickr.com/65535/51809703769_fc005d55fc_n.jpg",
        "link_img": "https://live.staticflickr.com/65535/51809703769_3c02e0cdc5_o.png",
        "id_image": "octagon_3810213"
      },
      {
        "link_thumb": "https://live.staticflickr.com/65535/51808393772_4a39bdaee4_n.jpg",
        "link_img": "https://live.staticflickr.com/65535/51808393772_224d2bb675_o.png",
        "id_image": "octagon_5854098"
      }
    ],
    "hash_code_list_img": "1969207576"
  },
  {
    "link_it": "https://github.com/lmbstudiocontact/lv_img_3500_it_3/raw/main/youth_lv_img_3500_it.json",
    "id_item": "youth_lv_img_3500_it",
    "id_album": "570943488",
    "english": "youth",
    "list_mean": [
      "thời kỳ đang trẻ (nhất là khoảng giữa thời thơ ấu và lúc trưởng thành); thời thanh niên; tuổi trẻ",
      "tầng lớp thanh niên; lứa tuổi thanh niên; (nói chung) thanh niên (cũng) the youth",
      "chàng trai trẻ; chàng thanh niên"
    ],
    "cau_en": "the youth of today has /have greater opportunities than ever before",
    "cau_vn": "lớp trẻ/giới trẻ ngày nay có những cơ hội lớn hơn bao giờ hết so với trước đây",
    "hash_code_list_mean": "1613174785",
    "list_img": [
      {
        "link_thumb": "https://live.staticflickr.com/65535/51808374982_34f9e968b7_n.jpg",
        "link_img": "https://live.staticflickr.com/65535/51808374982_5cdca0c5a0_o.png",
        "id_image": "youth_1312511"
      },
      {
        "link_thumb": "https://live.staticflickr.com/65535/51809685364_bb53ea09f6_n.jpg",
        "link_img": "https://live.staticflickr.com/65535/51809685364_1121dc6823_o.png",
        "id_image": "youth_3787893"
      },
      {
        "link_thumb": "https://live.staticflickr.com/65535/51809330266_aea7175f89_n.jpg",
        "link_img": "https://live.staticflickr.com/65535/51809330266_37831348b0_o.png",
        "id_image": "youth_4901028"
      }
    ],
    "hash_code_list_img": "-871557327"
  },
  {
    "link_it": "https://github.com/lmbstudiocontact/lv_img_3500_it_0/raw/main/ballot_lv_img_3500_it.json",
    "id_item": "ballot_lv_img_3500_it",
    "id_album": "570943488",
    "english": "ballot",
    "list_mean": [
      "như ballot-paper",
      "sự bỏ phiếu kín; hệ thống bỏ phiếu kín",
      "tổng số phiếu bầu ghi được trong lần bỏ phiếu kín",
      "( to ballot for somebody / something ) bỏ phiếu kín cho ai/cái gì",
      "( to ballot somebody about / on something ) cho ai phải bỏ phiếu kín về điều gì"
    ],
    "cau_en": "the union balloted its members on the proposed changes",
    "cau_vn": "liên đoàn đã cho các đoàn viên bỏ phiếu kín về những thay đổi đã đề nghị",
    "hash_code_list_mean": "608071799",
    "list_img": [
      {
        "link_thumb": "https://live.staticflickr.com/65535/51809672764_03b464798a_n.jpg",
        "link_img": "https://live.staticflickr.com/65535/51809672764_8a639709a5_o.png",
        "id_image": "ballot_1666054"
      },
      {
        "link_thumb": "https://live.staticflickr.com/65535/51808362387_d98443f692_n.jpg",
        "link_img": "https://live.staticflickr.com/65535/51808362387_077e7e230b_o.png",
        "id_image": "ballot_1844805"
      },
      {
        "link_thumb": "https://live.staticflickr.com/65535/51809317891_27fa8ee5e6_n.jpg",
        "link_img": "https://live.staticflickr.com/65535/51809317891_081d143daa_o.png",
        "id_image": "ballot_2472927"
      },
      {
        "link_thumb": "https://live.staticflickr.com/65535/51810054455_31789bd055_n.jpg",
        "link_img": "https://live.staticflickr.com/65535/51810054455_19f73b0839_o.png",
        "id_image": "ballot_4474030"
      },
      {
        "link_thumb": "https://live.staticflickr.com/65535/51810054590_c89959e5b4_n.jpg",
        "link_img": "https://live.staticflickr.com/65535/51810054590_e968a556ec_o.png",
        "id_image": "ballot_927297"
      }
    ],
    "hash_code_list_img": "-664082423"
  },
  {
    "link_it": "https://github.com/lmbstudiocontact/lv_img_3500_it_1/raw/main/jack_lv_img_3500_it.json",
    "id_item": "jack_lv_img_3500_it",
    "id_album": "570943488",
    "english": "jack",
    "list_mean": [
      "quả mít",
      "(thực vật học) cây mít",
      "gỗ mít",
      "(hàng hải) lá cờ ( (thường) chỉ quốc tịch)",
      "áo chẽn không tay (của lính)",
      "bình bằng da (để đựng nước, rượu...) ( (cũng) black jack )",
      "Giắc (tên riêng, cách gọi thân mật của tên Giôn)",
      "người con trai, gã ( (cũng) Jack )",
      "(như) jack tar",
      "nhân viên, thợ, người đi làm thuê làm mướn, người làm những công việc linh tinh ( (cũng) Jack )",
      "(đánh bài) quân J",
      "(quân sự), (từ lóng) lính quân cảnh",
      "(động vật học) cá chó nhỏ",
      "(kỹ thuật) cái kích, cái pa-lăng; tay đòn, đòn bẩy",
      "giá, bệ đỡ",
      "cái đế rút giày ống ( (cũng) boot jack )",
      "máy để quay xiên nướng thịt",
      "(từ Mỹ,nghĩa Mỹ) đuốc, đèn (để đi săn hoặc câu đêm) ( (cũng) jack light )",
      "( (thường) + up ) kích lên (xe ô tô...)",
      "săn bằng đuốc, săn bằng đèn; câu bằng đuốc, câu bằng đèn"
    ],
    "cau_en": "Jack and Gill (Jill )",
    "cau_vn": "chàng và nàng",
    "hash_code_list_mean": "1130477059",
    "list_img": [
      {
        "link_thumb": "https://live.staticflickr.com/65535/51809451498_2cc54368c5_n.jpg",
        "link_img": "https://live.staticflickr.com/65535/51809451498_0415f387a9_o.png",
        "id_image": "jack_217131"
      },
      {
        "link_thumb": "https://live.staticflickr.com/65535/51809451468_6c059fc769_n.jpg",
        "link_img": "https://live.staticflickr.com/65535/51809451468_fabe306d23_o.png",
        "id_image": "jack_287392"
      },
      {
        "link_thumb": "https://live.staticflickr.com/65535/51809336491_4a0667a6b3_n.jpg",
        "link_img": "https://live.staticflickr.com/65535/51809336491_75c848bcc2_o.png",
        "id_image": "jack_2906191"
      },
      {
        "link_thumb": "https://live.staticflickr.com/65535/51809451378_76b8e10020_n.jpg",
        "link_img": "https://live.staticflickr.com/65535/51809451378_3daff8f0f6_o.png",
        "id_image": "jack_3348007"
      },
      {
        "link_thumb": "https://live.staticflickr.com/65535/51808381437_d2a62b2a15_n.jpg",
        "link_img": "https://live.staticflickr.com/65535/51808381437_0d371c418e_o.png",
        "id_image": "jack_4284074"
      }
    ],
    "hash_code_list_img": "995919356"
  },
  {
    "link_it": "https://github.com/lmbstudiocontact/lv_img_3500_it_2/raw/main/plumb_lv_img_3500_it.json",
    "id_item": "plumb_lv_img_3500_it",
    "id_album": "570943488",
    "english": "plumb",
    "list_mean": [
      "quả dọi, hòn chì",
      "dây dọi; dây dò nước",
      "thế thẳng đứng, độ ngay (của tường...)",
      "thẳng đứng, ngay",
      "(nghĩa bóng) hoàn toàn, đích thật",
      "thẳng đứng, ngay",
      "(nghĩa bóng) đúng, chính xác",
      "(từ lóng) hoàn toàn, tuyệt đối",
      "dò độ sâu (biển, sông...) bằng dây dò; đo (độ sâu) bằng dây dò",
      "(nghĩa bóng) dò, thăm dò, dò xét",
      "làm thẳng đứng (bức tường...)",
      "làm nghề hàn chì"
    ],
    "cau_en": "plumb in the centre",
    "cau_vn": "ngay ở giữa, đúng ở giữa",
    "hash_code_list_mean": "-1831402960",
    "list_img": [
      {
        "link_thumb": "https://live.staticflickr.com/65535/51810077050_19e2ee2c18_n.jpg",
        "link_img": "https://live.staticflickr.com/65535/51810077050_c65a5d5379_o.png",
        "id_image": "plumb_3556115"
      }
    ],
    "hash_code_list_img": "2104139133"
  },
  {
    "link_it": "https://github.com/lmbstudiocontact/lv_img_3500_it_0/raw/main/comfort_lv_img_3500_it.json",
    "id_item": "comfort_lv_img_3500_it",
    "id_album": "570943488",
    "english": "comfort",
    "list_mean": [
      "sự an ủi; người an ủi; nguồn an ủi",
      "sự an nhàn; sự sung túc",
      "( số nhiều) tiện nghi",
      "(từ Mỹ,nghĩa Mỹ) chăn lông vịt",
      "dỗ dành; an ủi"
    ],
    "cau_en": "the hotel has all modern comforts /every modern comfort",
    "cau_vn": "khách sạn có đủ mọi tiện nghi hiện đại",
    "hash_code_list_mean": "641581744",
    "list_img": [
      {
        "link_thumb": "https://live.staticflickr.com/65535/51808364632_299262ef64_n.jpg",
        "link_img": "https://live.staticflickr.com/65535/51808364632_ae0ccf3801_o.png",
        "id_image": "comfort_5775234"
      }
    ],
    "hash_code_list_img": "1961718064"
  },
  {
    "link_it": "https://github.com/lmbstudiocontact/lv_img_3500_it_3/raw/main/slavery_lv_img_3500_it.json",
    "id_item": "slavery_lv_img_3500_it",
    "id_album": "570943488",
    "english": "slavery",
    "list_mean": [
      "cảnh nô lệ; sự nô lệ; tình trạng nô lệ",
      "sự chiếm hữu nô lệ; chế độ chiếm hữu nô lệ",
      "sự lao động vất vả; công việc cực nhọc, công việc được trả công rẻ mạt"
    ],
    "cau_en": "to prefer death to slavery",
    "cau_vn": "thà chết không chịu làm nô lệ",
    "hash_code_list_mean": "-1427050977",
    "list_img": [
      {
        "link_thumb": "https://live.staticflickr.com/65535/51810071400_e854166db2_n.jpg",
        "link_img": "https://live.staticflickr.com/65535/51810071400_a11c8a1733_o.png",
        "id_image": "slavery_1396585"
      },
      {
        "link_thumb": "https://live.staticflickr.com/65535/51809334426_4b077f731d_n.jpg",
        "link_img": "https://live.staticflickr.com/65535/51809334426_5d9dcbf1ac_o.png",
        "id_image": "slavery_3782230"
      },
      {
        "link_thumb": "https://live.staticflickr.com/65535/51809334396_96fe7a4132_n.jpg",
        "link_img": "https://live.staticflickr.com/65535/51809334396_33e27695e6_o.png",
        "id_image": "slavery_4110378"
      },
      {
        "link_thumb": "https://live.staticflickr.com/65535/51809334331_ee5df6150f_n.jpg",
        "link_img": "https://live.staticflickr.com/65535/51809334331_546f40676e_o.png",
        "id_image": "slavery_4484310"
      }
    ],
    "hash_code_list_img": "-720928430"
  },
  {
    "link_it": "https://github.com/lmbstudiocontact/lv_img_3500_it_1/raw/main/dose_lv_img_3500_it.json",
    "id_item": "dose_lv_img_3500_it",
    "id_album": "570943488",
    "english": "dose",
    "list_mean": [
      "lượng thuốc cần dùng mỗi lần; liều",
      "lượng phóng xạ mà ai/cái gì nhận được mỗi lần",
      "sự trải qua một cái gì khó chịu hoặc thú vị",
      "bệnh hoa liễu",
      "( to dose somebody / oneself with something ) cho ai/tự cho một liều gì"
    ],
    "cau_en": "a dose of flu , boring conversation , bad weather",
    "cau_vn": "một trận cúm, cuộc trò chuyện tẻ nhạt, đợt thời tiết xấu",
    "hash_code_list_mean": "1397424597",
    "list_img": [
      {
        "link_thumb": "https://live.staticflickr.com/65535/51808353007_9c5c81e7ee_n.jpg",
        "link_img": "https://live.staticflickr.com/65535/51808353007_7d13038e1e_o.png",
        "id_image": "dose_1488157"
      },
      {
        "link_thumb": "https://live.staticflickr.com/65535/51809664049_19263f6cd3_n.jpg",
        "link_img": "https://live.staticflickr.com/65535/51809664049_2d125b95d9_o.png",
        "id_image": "dose_2688622"
      },
      {
        "link_thumb": "https://live.staticflickr.com/65535/51810045775_b7f3b441ba_n.jpg",
        "link_img": "https://live.staticflickr.com/65535/51810045775_596c5650a9_o.png",
        "id_image": "dose_5671548"
      }
    ],
    "hash_code_list_img": "1065720264"
  },
  {
    "link_it": "https://github.com/lmbstudiocontact/lv_img_3500_it_0/raw/main/arrest_lv_img_3500_it.json",
    "id_item": "arrest_lv_img_3500_it",
    "id_album": "570943488",
    "english": "arrest",
    "list_mean": [
      "sự bắt giữ",
      "sự ngừng lại, sự chặn lại, sự hãm lại",
      "(pháp lý) sự hoãn thi hành",
      "bắt giữ",
      "làm ngừng lại, chặn lại, ngăn lại, hãm lại (máy đang chạy...)",
      "lôi cuốn (sự chú ý)",
      "(pháp lý) hoãn thi hành (một bản án vì có sự lầm lẫn)"
    ],
    "cau_en": "to arrest someone's attention",
    "cau_vn": "lôi cuốn sự chú ý của ai",
    "hash_code_list_mean": "-1368623173",
    "list_img": [
      {
        "link_thumb": "https://live.staticflickr.com/65535/51809305341_a007bccbe1_n.jpg",
        "link_img": "https://live.staticflickr.com/65535/51809305341_52972b2a9b_o.png",
        "id_image": "arrest_1901785"
      },
      {
        "link_thumb": "https://live.staticflickr.com/65535/51809660799_edc525859e_n.jpg",
        "link_img": "https://live.staticflickr.com/65535/51809660799_52afe78580_o.png",
        "id_image": "arrest_2399375"
      },
      {
        "link_thumb": "https://live.staticflickr.com/65535/51809420368_a0c5403c0b_n.jpg",
        "link_img": "https://live.staticflickr.com/65535/51809420368_c8295e7715_o.png",
        "id_image": "arrest_2670959"
      }
    ],
    "hash_code_list_img": "1150323269"
  },
  {
    "link_it": "https://github.com/lmbstudiocontact/lv_img_3500_it_3/raw/main/storehouse_lv_img_3500_it.json",
    "id_item": "storehouse_lv_img_3500_it",
    "id_album": "570943488",
    "english": "storehouse",
    "list_mean": [
      "nhà kho; vựa (đồ vật)",
      "(nghĩa bóng) tủ, kho (chứa đựng thông tin)"
    ],
    "cau_en": "a storehouse of information",
    "cau_vn": "một kho tài liệu",
    "hash_code_list_mean": "-1300302604",
    "list_img": [
      {
        "link_thumb": "https://live.staticflickr.com/65535/51808389907_75c42b519f_n.jpg",
        "link_img": "https://live.staticflickr.com/65535/51808389907_bdda115cdd_o.png",
        "id_image": "storehouse_351871"
      },
      {
        "link_thumb": "https://live.staticflickr.com/65535/51809344936_6780388daf_n.jpg",
        "link_img": "https://live.staticflickr.com/65535/51809344936_b3e6bdd5d0_o.png",
        "id_image": "storehouse_384012"
      },
      {
        "link_thumb": "https://live.staticflickr.com/65535/51809459703_9e3904a87f_n.jpg",
        "link_img": "https://live.staticflickr.com/65535/51809459703_eaf0fc0240_o.png",
        "id_image": "storehouse_5439106"
      }
    ],
    "hash_code_list_img": "-211230645"
  },
  {
    "link_it": "https://github.com/lmbstudiocontact/lv_img_3500_it_2/raw/main/obsolete_lv_img_3500_it.json",
    "id_item": "obsolete_lv_img_3500_it",
    "id_album": "570943488",
    "english": "obsolete",
    "list_mean": [
      "cổ xưa, quá hạn, đã lỗi thời",
      "(sinh vật học) teo đi",
      "người cổ",
      "vật cổ"
    ],
    "cau_en": "obsolete text-books",
    "cau_vn": "những sách giáo khoa không còn dùng được nữa",
    "hash_code_list_mean": "284894898",
    "list_img": [
      {
        "link_thumb": "https://live.staticflickr.com/65535/51809703984_cf25ab12b4_n.jpg",
        "link_img": "https://live.staticflickr.com/65535/51809703984_bb001e7424_o.png",
        "id_image": "obsolete_1610496"
      }
    ],
    "hash_code_list_img": "1950308578"
  },
  {
    "link_it": "https://github.com/lmbstudiocontact/lv_img_3500_it_1/raw/main/gender_lv_img_3500_it.json",
    "id_item": "gender_lv_img_3500_it",
    "id_album": "570943488",
    "english": "gender",
    "list_mean": [
      "(ngôn ngữ học) giống"
    ],
    "cau_en": "masculine gender",
    "cau_vn": "giống đực",
    "hash_code_list_mean": "831233377",
    "list_img": [
      {
        "link_thumb": "https://live.staticflickr.com/65535/51808381617_30ab793bdd_n.jpg",
        "link_img": "https://live.staticflickr.com/65535/51808381617_2ed392e688_o.png",
        "id_image": "gender_3939800"
      },
      {
        "link_thumb": "https://live.staticflickr.com/65535/51809336566_fce9eaf736_n.jpg",
        "link_img": "https://live.staticflickr.com/65535/51809336566_98bc864afe_o.png",
        "id_image": "gender_5759827"
      }
    ],
    "hash_code_list_img": "-2106289024"
  },
  {
    "link_it": "https://github.com/lmbstudiocontact/lv_img_3500_it_2/raw/main/oracle_lv_img_3500_it.json",
    "id_item": "oracle_lv_img_3500_it",
    "id_album": "570943488",
    "english": "oracle",
    "list_mean": [
      "(ở Hy Lạp thời cổ) nơi linh thiêng có thể xin thần thánh cho biết tương lai; đền thờ",
      "câu trả lời (tối nghĩa hoặc mập mờ); lời sấm",
      "tu sĩ đưa ra những lời sấm, lời tiên tri",
      "người được coi là có thể cho những lời khuyên đáng tin cậy; người có uy tín"
    ],
    "cau_en": "my sister's the oracle on beauty matters",
    "cau_vn": "chị tôi là người có uy tín về vấn đề chăm sóc sắc đẹp",
    "hash_code_list_mean": "-1738433018",
    "list_img": [
      {
        "link_thumb": "https://live.staticflickr.com/65535/51808389637_1e3e9d6c87_n.jpg",
        "link_img": "https://live.staticflickr.com/65535/51808389637_ff391daa66_o.png",
        "id_image": "oracle_6198665"
      }
    ],
    "hash_code_list_img": "1910491780"
  },
  {
    "link_it": "https://github.com/lmbstudiocontact/lv_img_3500_it_3/raw/main/worth_lv_img_3500_it.json",
    "id_item": "worth_lv_img_3500_it",
    "id_album": "570943488",
    "english": "worth",
    "list_mean": [
      "đáng giá, có một giá trị nào đó",
      "đáng, bõ công (có thể đem lại đền bù thoả đáng hoặc hài lòng nếu làm cái gì)",
      "có",
      "số lượng cái gì mua được bằng một khoản tiền nào đó",
      "số lượng cái gì kéo dài được trong một khoảng thời gian nào đó",
      "giá trị, tính hữu ích"
    ],
    "cau_en": "it's such a small point that it's hardly worth troubling about",
    "cau_vn": "đó là một điểm quá nhỏ hầu như không đáng phải bận tâm",
    "hash_code_list_mean": "-1157340987",
    "list_img": [
      {
        "link_thumb": "https://live.staticflickr.com/65535/51808378132_02bdb5a825_n.jpg",
        "link_img": "https://live.staticflickr.com/65535/51808378132_a98e3b5011_o.png",
        "id_image": "worth_1605307"
      },
      {
        "link_thumb": "https://live.staticflickr.com/65535/51809688259_79e60b6b35_n.jpg",
        "link_img": "https://live.staticflickr.com/65535/51809688259_e8aa580fbc_o.png",
        "id_image": "worth_4834034"
      }
    ],
    "hash_code_list_img": "-1811631591"
  },
  {
    "link_it": "https://github.com/lmbstudiocontact/lv_img_3500_it_0/raw/main/consult_lv_img_3500_it.json",
    "id_item": "consult_lv_img_3500_it",
    "id_album": "570943488",
    "english": "consult",
    "list_mean": [
      "( to consult somebody / something about something ) hỏi ý kiến; tra cứu, tham khảo",
      "( to consult with somebody ) bàn bạc với ai; hội ý với ai"
    ],
    "cau_en": "You should consult a doctor about your megrim",
    "cau_vn": "Anh nên nhờ bác sĩ khám chứng nhức nửa đầu của anh",
    "hash_code_list_mean": "753396135",
    "list_img": [
      {
        "link_thumb": "https://live.staticflickr.com/65535/51809308841_792fe2fa52_n.jpg",
        "link_img": "https://live.staticflickr.com/65535/51809308841_9630b4aea0_o.png",
        "id_image": "consultancy_5235368"
      },
      {
        "link_thumb": "https://live.staticflickr.com/65535/51809308921_7743b0a4c0_n.jpg",
        "link_img": "https://live.staticflickr.com/65535/51809308921_198b4e1a65_o.png",
        "id_image": "consult_1440969"
      },
      {
        "link_thumb": "https://live.staticflickr.com/65535/51809308886_7d11e681a4_n.jpg",
        "link_img": "https://live.staticflickr.com/65535/51809308886_39bf78b190_o.png",
        "id_image": "consult_1900168"
      },
      {
        "link_thumb": "https://live.staticflickr.com/65535/51808353092_23ab4151cd_n.jpg",
        "link_img": "https://live.staticflickr.com/65535/51808353092_a9bf7f3376_o.png",
        "id_image": "consult_2452638"
      },
      {
        "link_thumb": "https://live.staticflickr.com/65535/51810045860_6c713d312e_n.jpg",
        "link_img": "https://live.staticflickr.com/65535/51810045860_44c244917b_o.png",
        "id_image": "consult_2746329"
      }
    ],
    "hash_code_list_img": "640654722"
  },
  {
    "link_it": "https://github.com/lmbstudiocontact/lv_img_3500_it_0/raw/main/caper_lv_img_3500_it.json",
    "id_item": "caper_lv_img_3500_it",
    "id_album": "570943488",
    "english": "caper",
    "list_mean": [
      "(thực vật học) cây bạch hoa",
      "( số nhiều) nụ bạch hoa giầm (để chế nước sốt)",
      "sự nhảy cỡn, sự nhảy lò cò",
      "( số nhiều) hành vi dại dột; hành động kỳ cục",
      "nhảy cỡn, nhảy lò cò",
      "hành động dại dột; hành động kỳ cục"
    ],
    "cau_en": "to cut capers ; to cut a caper",
    "cau_vn": "nhảy cỡn",
    "hash_code_list_mean": "-1601498643",
    "list_img": [
      {
        "link_thumb": "https://live.staticflickr.com/65535/51809328836_4cb53b61cd_n.jpg",
        "link_img": "https://live.staticflickr.com/65535/51809328836_eb3993fd33_o.png",
        "id_image": "capers_6108931"
      },
      {
        "link_thumb": "https://live.staticflickr.com/65535/51808373642_0c3c115e5b_n.jpg",
        "link_img": "https://live.staticflickr.com/65535/51808373642_572a85ea9e_o.png",
        "id_image": "caper_1135504"
      }
    ],
    "hash_code_list_img": "199282483"
  },
  {
    "link_it": "https://github.com/lmbstudiocontact/lv_img_3500_it_0/raw/main/chubby_lv_img_3500_it.json",
    "id_item": "chubby_lv_img_3500_it",
    "id_album": "570943488",
    "english": "chubby",
    "list_mean": [
      "mũm mĩm, mập mạp, phinh phính (má)"
    ],
    "cau_en": "chubby cheeks",
    "cau_vn": "má phinh phính",
    "hash_code_list_mean": "-1829450116",
    "list_img": [
      {
        "link_thumb": "https://live.staticflickr.com/65535/51810044210_26fa013728_n.jpg",
        "link_img": "https://live.staticflickr.com/65535/51810044210_ca37473d7e_o.png",
        "id_image": "chubby_1818370"
      },
      {
        "link_thumb": "https://live.staticflickr.com/65535/51809422343_5d343e6cef_n.jpg",
        "link_img": "https://live.staticflickr.com/65535/51809422343_10d8af63d8_o.png",
        "id_image": "chubby_5571374"
      }
    ],
    "hash_code_list_img": "-387590487"
  },
  {
    "link_it": "https://github.com/lmbstudiocontact/lv_img_3500_it_0/raw/main/auction_lv_img_3500_it.json",
    "id_item": "auction_lv_img_3500_it",
    "id_album": "570943488",
    "english": "auction",
    "list_mean": [
      "sự bán đấu giá; cuộc bán đấu giá (cũng) auction sale",
      "bán đấu giá"
    ],
    "cau_en": "the house is up for auction /will be sold by auction",
    "cau_vn": "ngôi nhà được đem bán đấu giá/sẽ được bán đấu giá",
    "hash_code_list_mean": "-1034453359",
    "list_img": [
      {
        "link_thumb": "https://live.staticflickr.com/65535/51808372212_5ffe881b3e_n.jpg",
        "link_img": "https://live.staticflickr.com/65535/51808372212_b6f8028e5e_o.png",
        "id_image": "auctions_4668524"
      },
      {
        "link_thumb": "https://live.staticflickr.com/65535/51809327596_24a9cc8ed6_n.jpg",
        "link_img": "https://live.staticflickr.com/65535/51809327596_fff7f8d473_o.png",
        "id_image": "auction_2720484"
      },
      {
        "link_thumb": "https://live.staticflickr.com/65535/51809327666_8fab0dce1e_n.jpg",
        "link_img": "https://live.staticflickr.com/65535/51809327666_69e5569fb6_o.png",
        "id_image": "auction_411716"
      }
    ],
    "hash_code_list_img": "1853043813"
  },
  {
    "link_it": "https://github.com/lmbstudiocontact/lv_img_3500_it_2/raw/main/nest_lv_img_3500_it.json",
    "id_item": "nest_lv_img_3500_it",
    "id_album": "570943488",
    "english": "nest",
    "list_mean": [
      "tổ, ổ (chim, chuột...)",
      "nơi ẩn náu, sào huyệt (trộm cướp...)",
      "bộ đồ xếp lồng vào nhau",
      "làm tổ",
      "tìm tổ chim, bắt tổ chim",
      "ẩn núp, ẩn mình",
      "đặt vào ổ",
      "( (thường) động tính từ quá khứ) xếp lồng vào nhau",
      "(kỹ thuật) lắp (mộng)"
    ],
    "cau_en": "a nest of pirates",
    "cau_vn": "sào huyệt kẻ cướp",
    "hash_code_list_mean": "-209019121",
    "list_img": [
      {
        "link_thumb": "https://live.staticflickr.com/65535/51809439393_0483b6d649_n.jpg",
        "link_img": "https://live.staticflickr.com/65535/51809439393_a6c53152d0_o.png",
        "id_image": "nest_1809034"
      },
      {
        "link_thumb": "https://live.staticflickr.com/65535/51808369292_85b592823c_n.jpg",
        "link_img": "https://live.staticflickr.com/65535/51808369292_1be490eb59_o.png",
        "id_image": "nest_183958"
      },
      {
        "link_thumb": "https://live.staticflickr.com/65535/51809439358_80f1664592_n.jpg",
        "link_img": "https://live.staticflickr.com/65535/51809439358_193d5b0cd3_o.png",
        "id_image": "nest_2851878"
      },
      {
        "link_thumb": "https://live.staticflickr.com/65535/51809324381_a87759d5b2_n.jpg",
        "link_img": "https://live.staticflickr.com/65535/51809324381_1b57405267_o.png",
        "id_image": "nest_427432"
      }
    ],
    "hash_code_list_img": "-481932667"
  },
  {
    "link_it": "https://github.com/lmbstudiocontact/lv_img_3500_it_0/raw/main/continuity_lv_img_3500_it.json",
    "id_item": "continuity_lv_img_3500_it",
    "id_album": "570943488",
    "english": "continuity",
    "list_mean": [
      "sự liên tục, sự liên tiếp; tính liên tục",
      "kịch bản điện ảnh"
    ],
    "cau_en": "the principle of continuity",
    "cau_vn": "nguyên tắc liên tục",
    "hash_code_list_mean": "2032254332",
    "list_img": [
      {
        "link_thumb": "https://live.staticflickr.com/65535/51808350987_2aebd6e4fd_n.jpg",
        "link_img": "https://live.staticflickr.com/65535/51808350987_e5c265712d_o.png",
        "id_image": "continuous_1768935"
      },
      {
        "link_thumb": "https://live.staticflickr.com/65535/51809306721_a00399215b_n.jpg",
        "link_img": "https://live.staticflickr.com/65535/51809306721_27d597b8df_o.png",
        "id_image": "continuous_4098110"
      }
    ],
    "hash_code_list_img": "153742801"
  },
  {
    "link_it": "https://github.com/lmbstudiocontact/lv_img_3500_it_1/raw/main/juggle_lv_img_3500_it.json",
    "id_item": "juggle_lv_img_3500_it",
    "id_album": "570943488",
    "english": "juggle",
    "list_mean": [
      "trò tung hứng; trò xiếc",
      "sự lừa bịp, sự lừa gạt",
      "( to juggle with something ) tung (đồ vật, nhất là những quả bóng) lên trên không, bắt lấy chúng rồi lại tung chúng lên nữa, cứ thế mãi, sao cho luôn có một quả bóng ở trên không; tung hứng",
      "( to juggle with something ) sắp đặt lại; tráo trở",
      "lừa bịp; dùng mánh khoé để lừa"
    ],
    "cau_en": "the government juggled with the figures and facts to hide political stability",
    "cau_vn": "chính phủ tráo trở các số liệu và sự kiện để che giấu tình trạng bất ổn về chính trị",
    "hash_code_list_mean": "-1011908811",
    "list_img": [
      {
        "link_thumb": "https://live.staticflickr.com/65535/51808376082_5ffbd5957d_n.jpg",
        "link_img": "https://live.staticflickr.com/65535/51808376082_64f16e0857_o.png",
        "id_image": "juggle_1680803"
      },
      {
        "link_thumb": "https://live.staticflickr.com/65535/51809686434_229f2eaa94_n.jpg",
        "link_img": "https://live.staticflickr.com/65535/51809686434_c33c1e6d13_o.png",
        "id_image": "juggle_947861"
      }
    ],
    "hash_code_list_img": "417844942"
  },
  {
    "link_it": "https://github.com/lmbstudiocontact/lv_img_3500_it_3/raw/main/tip_lv_img_3500_it.json",
    "id_item": "tip_lv_img_3500_it",
    "id_album": "570943488",
    "english": "tip",
    "list_mean": [
      "đầu, mút, đỉnh, chóp",
      "đầu bịt (của gậy...)",
      "đầu ngậm của điếu thuốc lá",
      "bút để thếp vàng",
      "bịt đầu, lắp đầu vào",
      "tiền quà, tiền diêm thuốc",
      "lời khuyên, lời mách nước (đánh cá ngựa)",
      "mẹo, mánh lới, mánh khoé",
      "cho tiền quà, cho tiền diêm thuốc",
      "mách nước (đánh cá ngựa)",
      "(thông tục) đưa cho, trao",
      "cái đánh nhẹ, cái gảy nhẹ, cái đẩy nhẹ, cái chạm nhẹ, cái vỗ nhẹ",
      "đánh nhẹ, gảy nhẹ, đẩy nhẹ, chạm nhẹ, vỗ nhẹ",
      "nơi đổ rác, thùng rác, bãi rác",
      "(thông tục) nơi bẩn thỉu, nơi lộn xộn",
      "lật nghiêng, làm nghiêng; đổ, rót"
    ],
    "cau_en": "their house is an absolute tip",
    "cau_vn": "ngôi nhà của họ là nơi rất lộn xộn",
    "hash_code_list_mean": "989900003",
    "list_img": [
      {
        "link_thumb": "https://live.staticflickr.com/65535/51809461618_e082856338_n.jpg",
        "link_img": "https://live.staticflickr.com/65535/51809461618_936eac4b9f_o.png",
        "id_image": "tip_1900292"
      },
      {
        "link_thumb": "https://live.staticflickr.com/65535/51809461593_66b0d78dbf_n.jpg",
        "link_img": "https://live.staticflickr.com/65535/51809461593_64bbd1a212_o.png",
        "id_image": "tip_2132655"
      },
      {
        "link_thumb": "https://live.staticflickr.com/65535/51808391792_05cd1e5b1d_n.jpg",
        "link_img": "https://live.staticflickr.com/65535/51808391792_5926216293_o.png",
        "id_image": "tip_705108"
      }
    ],
    "hash_code_list_img": "-2027526581"
  },
  {
    "link_it": "https://github.com/lmbstudiocontact/lv_img_3500_it_3/raw/main/yawn_lv_img_3500_it.json",
    "id_item": "yawn_lv_img_3500_it",
    "id_album": "570943488",
    "english": "yawn",
    "list_mean": [
      "cử chỉ ngáp",
      "(kỹ thuật) khe hở",
      "há miệng, toác ra, mở ra (đồ vật)",
      "vừa nói vừa ngáp"
    ],
    "cau_en": "\"its' very late \", he yawned",
    "cau_vn": "anh ta vừa ngáp vừa nói \"khuya lắm rồi\"",
    "hash_code_list_mean": "1342171549",
    "list_img": [
      {
        "link_thumb": "https://live.staticflickr.com/65535/51809446223_3b6453653b_n.jpg",
        "link_img": "https://live.staticflickr.com/65535/51809446223_71558d0bfd_o.png",
        "id_image": "yawn_1128905"
      },
      {
        "link_thumb": "https://live.staticflickr.com/65535/51809686234_b1b02020e2_n.jpg",
        "link_img": "https://live.staticflickr.com/65535/51809686234_ee161247ab_o.png",
        "id_image": "yawn_1128961"
      },
      {
        "link_thumb": "https://live.staticflickr.com/65535/51809686189_c342a944f9_n.jpg",
        "link_img": "https://live.staticflickr.com/65535/51809686189_6f63606c98_o.png",
        "id_image": "yawn_5509051"
      }
    ],
    "hash_code_list_img": "-960614361"
  },
  {
    "link_it": "https://github.com/lmbstudiocontact/lv_img_3500_it_2/raw/main/robotic_lv_img_3500_it.json",
    "id_item": "robotic_lv_img_3500_it",
    "id_album": "570943488",
    "english": "robotic",
    "list_mean": [
      "như người máy; cứng nhắc, máy móc"
    ],
    "cau_en": "robotic movements",
    "cau_vn": "những động tác như người máy",
    "hash_code_list_mean": "-1638830719",
    "list_img": [
      {
        "link_thumb": "https://live.staticflickr.com/65535/51809459243_63679cb594_n.jpg",
        "link_img": "https://live.staticflickr.com/65535/51809459243_50671af59f_o.png",
        "id_image": "robotic_2317074"
      },
      {
        "link_thumb": "https://live.staticflickr.com/65535/51808389367_a6327a34f6_n.jpg",
        "link_img": "https://live.staticflickr.com/65535/51808389367_1bc1f4c09b_o.png",
        "id_image": "robotic_2861690"
      },
      {
        "link_thumb": "https://live.staticflickr.com/65535/51810081785_daa046ff8b_n.jpg",
        "link_img": "https://live.staticflickr.com/65535/51810081785_415173aea4_o.png",
        "id_image": "robotic_6375665"
      }
    ],
    "hash_code_list_img": "-76038933"
  },
  {
    "link_it": "https://github.com/lmbstudiocontact/lv_img_3500_it_2/raw/main/pendant_lv_img_3500_it.json",
    "id_item": "pendant_lv_img_3500_it",
    "id_album": "570943488",
    "english": "pendant",
    "list_mean": [
      "mặt dây chuyền",
      "miếng thủy tinh (trang trí đèn treo nhiều ngọn)",
      "(hàng hải) cờ hiệu (trên cột buồm) (như) pennant",
      "(hàng hải) cờ đuôi nheo",
      "vật giống, vật đối xứng",
      "vật được treo",
      "trang sức đeo lòng thòng; vòng; hoa tai; đèn treo",
      "giá treo",
      "sự treo",
      "dây móc thòng lọng",
      "đèn điện treo (từ trần)",
      "bộ phận phụ",
      "xem pendent"
    ],
    "cau_en": "to be a pendant to ...",
    "cau_vn": "là vật đối xứng của...",
    "hash_code_list_mean": "-1122425268",
    "list_img": [
      {
        "link_thumb": "https://live.staticflickr.com/65535/51808367607_f7d3e6a6a8_n.jpg",
        "link_img": "https://live.staticflickr.com/65535/51808367607_eaa3543fa0_o.png",
        "id_image": "pendant_4580912"
      },
      {
        "link_thumb": "https://live.staticflickr.com/65535/51808367587_23f4efb1f8_n.jpg",
        "link_img": "https://live.staticflickr.com/65535/51808367587_b5ecb87b07_o.png",
        "id_image": "pendant_4581024"
      },
      {
        "link_thumb": "https://live.staticflickr.com/65535/51808367552_f8182b9774_n.jpg",
        "link_img": "https://live.staticflickr.com/65535/51808367552_b84f790b18_o.png",
        "id_image": "pendant_4637471"
      }
    ],
    "hash_code_list_img": "-716410677"
  },
  {
    "link_it": "https://github.com/lmbstudiocontact/lv_img_3500_it_1/raw/main/gang_lv_img_3500_it.json",
    "id_item": "gang_lv_img_3500_it",
    "id_album": "570943488",
    "english": "gang",
    "list_mean": [
      "đoàn, tốp, toán, kíp",
      "bọn, lũ",
      "bộ (đồ nghề...)",
      "họp thành bọn; kéo bè kéo bọn ( (cũng) to gang up )",
      "sắp xếp (đồ nghề...) thành bộ"
    ],
    "cau_en": "a gang of war prisoners",
    "cau_vn": "một đoàn tù binh",
    "hash_code_list_mean": "-746431623",
    "list_img": [
      {
        "link_thumb": "https://live.staticflickr.com/65535/51809454478_5ba9d9bae3_n.jpg",
        "link_img": "https://live.staticflickr.com/65535/51809454478_8aeb443f66_o.png",
        "id_image": "gang_2495707"
      }
    ],
    "hash_code_list_img": "774676035"
  },
  {
    "link_it": "https://github.com/lmbstudiocontact/lv_img_3500_it_2/raw/main/oleander_lv_img_3500_it.json",
    "id_item": "oleander_lv_img_3500_it",
    "id_album": "570943488",
    "english": "oleander",
    "list_mean": [
      "(thực vật học) cây trúc đào"
    ],
    "cau_en": "oleander has red or white flowers and hard leaf",
    "cau_vn": "cây trúc đào có những hoa màu đỏ hoặc màu trắng và lá ráp cứng",
    "hash_code_list_mean": "1969999788",
    "list_img": [
      {
        "link_thumb": "https://live.staticflickr.com/65535/51809496823_e19c3f35fb_n.jpg",
        "link_img": "https://live.staticflickr.com/65535/51809496823_11d0057495_o.png",
        "id_image": "oleander_4759173"
      }
    ],
    "hash_code_list_img": "1037201717"
  },
  {
    "link_it": "https://github.com/lmbstudiocontact/lv_img_3500_it_0/raw/main/diagnostic_lv_img_3500_it.json",
    "id_item": "diagnostic_lv_img_3500_it",
    "id_album": "570943488",
    "english": "diagnostic",
    "list_mean": [
      "chẩn đoán",
      "(y học) triệu chứng",
      "phép chẩn đoán; chẩn đoán học"
    ],
    "cau_en": "symptoms that were of little diagnostic value",
    "cau_vn": "những triệu chứng ít có giá trị cho việc chẩn đoán",
    "hash_code_list_mean": "1993477418",
    "list_img": [
      {
        "link_thumb": "https://live.staticflickr.com/65535/51809439708_9b2b18fc32_n.jpg",
        "link_img": "https://live.staticflickr.com/65535/51809439708_3c98048c16_o.png",
        "id_image": "diagnostic_1656962"
      },
      {
        "link_thumb": "https://live.staticflickr.com/65535/51809679799_dc7dc3385a_n.jpg",
        "link_img": "https://live.staticflickr.com/65535/51809679799_44e85bda8b_o.png",
        "id_image": "diagnostic_2631398"
      },
      {
        "link_thumb": "https://live.staticflickr.com/65535/51810061480_84fbdc99e0_n.jpg",
        "link_img": "https://live.staticflickr.com/65535/51810061480_751f4500d7_o.png",
        "id_image": "diagnostic_3998071"
      },
      {
        "link_thumb": "https://live.staticflickr.com/65535/51809679714_e2b2fdf58a_n.jpg",
        "link_img": "https://live.staticflickr.com/65535/51809679714_cc139fc8b9_o.png",
        "id_image": "diagnostic_5154792"
      },
      {
        "link_thumb": "https://live.staticflickr.com/65535/51809679874_c1aed5c16a_n.jpg",
        "link_img": "https://live.staticflickr.com/65535/51809679874_5f4913b332_o.png",
        "id_image": "diagnostic_670800"
      }
    ],
    "hash_code_list_img": "2048610186"
  },
  {
    "link_it": "https://github.com/lmbstudiocontact/lv_img_3500_it_0/raw/main/clinic_lv_img_3500_it.json",
    "id_item": "clinic_lv_img_3500_it",
    "id_album": "570943488",
    "english": "clinic",
    "list_mean": [
      "bệnh viện tư hoặc chuyên khoa",
      "phòng khám chữa bệnh (nhất là dành cho bệnh nhân ngoại trú)",
      "bài giảng lâm sàng; sự thực tập lâm sàng"
    ],
    "cau_en": "dental /diabetic clinic",
    "cau_vn": "khoa răng/tiểu đường",
    "hash_code_list_mean": "-1197720251",
    "list_img": [
      {
        "link_thumb": "https://live.staticflickr.com/65535/51809686739_268b6ba059_n.jpg",
        "link_img": "https://live.staticflickr.com/65535/51809686739_eb8006b73b_o.png",
        "id_image": "clinic_2278465"
      },
      {
        "link_thumb": "https://live.staticflickr.com/65535/51808376442_c80e9e6017_n.jpg",
        "link_img": "https://live.staticflickr.com/65535/51808376442_d58e002a7d_o.png",
        "id_image": "clinic_2682062"
      },
      {
        "link_thumb": "https://live.staticflickr.com/65535/51809686674_ef381cc941_n.jpg",
        "link_img": "https://live.staticflickr.com/65535/51809686674_2fc400f70d_o.png",
        "id_image": "clinic_3028573"
      },
      {
        "link_thumb": "https://live.staticflickr.com/65535/51808376337_7becd35e85_n.jpg",
        "link_img": "https://live.staticflickr.com/65535/51808376337_800688f715_o.png",
        "id_image": "clinic_3111563"
      },
      {
        "link_thumb": "https://live.staticflickr.com/65535/51810068300_c7c796d9eb_n.jpg",
        "link_img": "https://live.staticflickr.com/65535/51810068300_8f4f582a79_o.png",
        "id_image": "clinic_5266434"
      }
    ],
    "hash_code_list_img": "-88551290"
  },
  {
    "link_it": "https://github.com/lmbstudiocontact/lv_img_3500_it_3/raw/main/shaver_lv_img_3500_it.json",
    "id_item": "shaver_lv_img_3500_it",
    "id_album": "570943488",
    "english": "shaver",
    "list_mean": [
      "người cạo, thợ cạo",
      "dao cạo (điện, pin) (như) electric razor",
      "(từ Mỹ,nghĩa Mỹ), (thông tục) người khó mặc cả, người khó chơi (trong chuyện làm ăn)",
      "(thông tục) chàng trai; cậu bé"
    ],
    "cau_en": "you cheeky young shaver !",
    "cau_vn": "mày là thằng nhãi láo xược!",
    "hash_code_list_mean": "-1979876858",
    "list_img": [
      {
        "link_thumb": "https://live.staticflickr.com/65535/51809346366_540994d9dc_n.jpg",
        "link_img": "https://live.staticflickr.com/65535/51809346366_a2aba8ac59_o.png",
        "id_image": "shaver_1267835"
      },
      {
        "link_thumb": "https://live.staticflickr.com/65535/51809346311_b943295d9e_n.jpg",
        "link_img": "https://live.staticflickr.com/65535/51809346311_f2b1622834_o.png",
        "id_image": "shaver_3791209"
      }
    ],
    "hash_code_list_img": "-298867386"
  },
  {
    "link_it": "https://github.com/lmbstudiocontact/lv_img_3500_it_3/raw/main/sharp_lv_img_3500_it.json",
    "id_item": "sharp_lv_img_3500_it",
    "id_album": "570943488",
    "english": "sharp",
    "list_mean": [
      "sắc, nhọn, bén",
      "rõ nghĩa, dễ nhận, rõ ràng, sắc nét",
      "thình lình, đột ngột (về đoạn cong, đường cong, dốc..)",
      "lanh lảnh, chói tai, the thé (về âm thanh)",
      "cay, hắc, gắt, hăng, tạo ra một cảm giác mạnh (về mùi, vị)",
      "buốt, nhói (về cơn đau, cơn lạnh)",
      "tinh, thính, nhạy, thông minh, sắc sảo",
      "cao (về âm thanh, nhạc cụ..)",
      "thăng, cao nửa cung (về nốt nhạc)",
      "chỉ trích gay gắt",
      "ma mảnh, bất chính, thiếu đạo đức",
      "nhanh chóng, mau mắn, mạnh mẽ",
      "(ngôn ngữ học) điếc, không kêu",
      "(thông tục) diện, chải chuốt",
      "kim khâu mũi thật nhọn",
      "(ngôn ngữ học) phụ âm điếc",
      "(âm nhạc) nốt thăng; dấu thăng",
      "(thông tục) người lừa đảo, người cờ gian bạc lận",
      "(đùa cợt) chuyên gia, người thạo (về cái gì)",
      "( số nhiều) (nông nghiệp) tấm, hạt tấm",
      "sắc cạnh, sắc nhọn",
      "(thông tục) đúng",
      "(thông tục) đột ngột, bất thình lình; sững, vụt, đột",
      "(âm nhạc) cao quá độ cao đúng"
    ],
    "cau_en": "the sharp taste of lemon juice",
    "cau_vn": "vị chua gắt của nước chanh",
    "hash_code_list_mean": "-1775113255",
    "list_img": [
      {
        "link_thumb": "https://live.staticflickr.com/65535/51809701504_f075cf2073_n.jpg",
        "link_img": "https://live.staticflickr.com/65535/51809701504_3786df5168_o.png",
        "id_image": "sharpen_648411"
      },
      {
        "link_thumb": "https://live.staticflickr.com/65535/51808391647_bf8155c0be_n.jpg",
        "link_img": "https://live.staticflickr.com/65535/51808391647_9212de4c26_o.png",
        "id_image": "sharp_215046"
      }
    ],
    "hash_code_list_img": "-1343075137"
  },
  {
    "link_it": "https://github.com/lmbstudiocontact/lv_img_3500_it_0/raw/main/chairman_lv_img_3500_it.json",
    "id_item": "chairman_lv_img_3500_it",
    "id_album": "570943488",
    "english": "chairman",
    "list_mean": [
      "người điều khiển một cuộc họp; chủ toạ; chủ tịch",
      "người thường xuyên điều khiển một ủy ban, một hội đồng..."
    ],
    "cau_en": "chairman of the board of governors (of a school )",
    "cau_vn": "chủ tịch hội đồng quản trị (một trường học)",
    "hash_code_list_mean": "1888030192",
    "list_img": [
      {
        "link_thumb": "https://live.staticflickr.com/65535/51809315371_f14ef3b99d_n.jpg",
        "link_img": "https://live.staticflickr.com/65535/51809315371_e2cf15f1a8_o.png",
        "id_image": "chairman_2361599"
      }
    ],
    "hash_code_list_img": "148802342"
  },
  {
    "link_it": "https://github.com/lmbstudiocontact/lv_img_3500_it_1/raw/main/funny_lv_img_3500_it.json",
    "id_item": "funny_lv_img_3500_it",
    "id_album": "570943488",
    "english": "funny",
    "list_mean": [
      "buồn cười, ngồ ngộ, khôi hài",
      "là lạ, khang khác",
      "(thông tục) lời nói buồn cười; câu chuyện khôi hài",
      "( số nhiều) tập tranh khôi hài, tập tranh vui",
      "thuyền một người chèo"
    ],
    "cau_en": "there's something funny about this affair",
    "cau_vn": "có một cái gì là lạ trong việc này",
    "hash_code_list_mean": "-2102103390",
    "list_img": [
      {
        "link_thumb": "https://live.staticflickr.com/65535/51809456418_19fea73eb7_n.jpg",
        "link_img": "https://live.staticflickr.com/65535/51809456418_b19429537e_o.png",
        "id_image": "funny_2173889"
      },
      {
        "link_thumb": "https://live.staticflickr.com/65535/51809341551_3c54842338_n.jpg",
        "link_img": "https://live.staticflickr.com/65535/51809341551_a55d271782_o.png",
        "id_image": "funny_2978195"
      },
      {
        "link_thumb": "https://live.staticflickr.com/65535/51810078980_e7c17afe39_n.jpg",
        "link_img": "https://live.staticflickr.com/65535/51810078980_bc89a302f1_o.png",
        "id_image": "funny_4138870"
      }
    ],
    "hash_code_list_img": "-958309731"
  },
  {
    "link_it": "https://github.com/lmbstudiocontact/lv_img_3500_it_2/raw/main/night_lv_img_3500_it.json",
    "id_item": "night_lv_img_3500_it",
    "id_album": "570943488",
    "english": "night",
    "list_mean": [
      "đêm, tối, cảnh tối tăm"
    ],
    "cau_en": "to have (pass ) a good night",
    "cau_vn": "đêm ngủ ngon",
    "hash_code_list_mean": "643675963",
    "list_img": [
      {
        "link_thumb": "https://live.staticflickr.com/65535/51810059420_f941407059_n.jpg",
        "link_img": "https://live.staticflickr.com/65535/51810059420_dc6d93ed26_o.png",
        "id_image": "night_203768"
      },
      {
        "link_thumb": "https://live.staticflickr.com/65535/51809437888_ca2404361e_n.jpg",
        "link_img": "https://live.staticflickr.com/65535/51809437888_8db8407a99_o.png",
        "id_image": "night_203808"
      },
      {
        "link_thumb": "https://live.staticflickr.com/65535/51809322571_a1b1f5c96f_n.jpg",
        "link_img": "https://live.staticflickr.com/65535/51809322571_3ba651eb51_o.png",
        "id_image": "night_5079909"
      }
    ],
    "hash_code_list_img": "573778311"
  },
  {
    "link_it": "https://github.com/lmbstudiocontact/lv_img_3500_it_1/raw/main/earth_lv_img_3500_it.json",
    "id_item": "earth_lv_img_3500_it",
    "id_album": "570943488",
    "english": "earth",
    "list_mean": [
      "đất, mặt đất, quả đất",
      "(hoá học) đất",
      "hang (cáo, chồn...)",
      "trần gian, cõi tục (đối với thiên đường, địa ngục)",
      "vun (cây); lấp đất (hạt giống)",
      "đuổi (cáo...) vào hang",
      "chạy vào hang (cáo...)",
      "(điện học) đặt dây đất, nối với đất"
    ],
    "cau_en": "to go to earth",
    "cau_vn": "chui vào tận hang",
    "hash_code_list_mean": "-792466442",
    "list_img": [
      {
        "link_thumb": "https://live.staticflickr.com/65535/51810069445_7b66d1e5a1_n.jpg",
        "link_img": "https://live.staticflickr.com/65535/51810069445_8b79ec126a_o.png",
        "id_image": "earth_169789"
      },
      {
        "link_thumb": "https://live.staticflickr.com/65535/51809447608_264086f415_n.jpg",
        "link_img": "https://live.staticflickr.com/65535/51809447608_a608209bf6_o.png",
        "id_image": "earth_721081"
      },
      {
        "link_thumb": "https://live.staticflickr.com/65535/51809687529_d3e1b020a6_n.jpg",
        "link_img": "https://live.staticflickr.com/65535/51809687529_0e706304b3_o.png",
        "id_image": "earth_825001"
      }
    ],
    "hash_code_list_img": "-319257108"
  },
  {
    "link_it": "https://github.com/lmbstudiocontact/lv_img_3500_it_0/raw/main/acoustic_lv_img_3500_it.json",
    "id_item": "acoustic_lv_img_3500_it",
    "id_album": "570943488",
    "english": "acoustic",
    "list_mean": [
      "(thuộc) âm thanh; (thuộc) âm học",
      "(thuộc) thính giác",
      "không dùng điện (nhạc cụ)"
    ],
    "cau_en": "acoustic nerves",
    "cau_vn": "dây thần kinh thính giác",
    "hash_code_list_mean": "1926369940",
    "list_img": [
      {
        "link_thumb": "https://live.staticflickr.com/65535/51810060150_431c422646_n.jpg",
        "link_img": "https://live.staticflickr.com/65535/51810060150_86cca090a1_o.png",
        "id_image": "acoustic_352256"
      }
    ],
    "hash_code_list_img": "1098082359"
  },
  {
    "link_it": "https://github.com/lmbstudiocontact/lv_img_3500_it_0/raw/main/broadcast_lv_img_3500_it.json",
    "id_item": "broadcast_lv_img_3500_it",
    "id_album": "570943488",
    "english": "broadcast",
    "list_mean": [
      "(nói về tin tức...) được loan truyền qua đài phát thanh hoặc đài truyền hình",
      "phát (tin tức...) bằng cách truyền thanh hoặc truyền hình",
      "nói hoặc xuất hiện trên truyền thanh hoặc truyền hình",
      "phổ biến rộng rãi; quảng bá",
      "gieo (hạt) bằng cách rải",
      "chương trình phát thanh hoặc truyền hình"
    ],
    "cau_en": "to broadcast the up-to-the-minute news , a fashion show , a football match",
    "cau_vn": "phát tin giờ chót, một buổi trình diễn thời trang, một trận bóng đá",
    "hash_code_list_mean": "-25456925",
    "list_img": [
      {
        "link_thumb": "https://live.staticflickr.com/65535/51809315726_8195aa7171_n.jpg",
        "link_img": "https://live.staticflickr.com/65535/51809315726_f7fb0e969e_o.png",
        "id_image": "broadcast_2396257"
      },
      {
        "link_thumb": "https://live.staticflickr.com/65535/51808359872_1b294db17b_n.jpg",
        "link_img": "https://live.staticflickr.com/65535/51808359872_4bbf3aebcf_o.png",
        "id_image": "broadcast_4318954"
      },
      {
        "link_thumb": "https://live.staticflickr.com/65535/51809670319_a1854955cf_n.jpg",
        "link_img": "https://live.staticflickr.com/65535/51809670319_eb848ce1b1_o.png",
        "id_image": "broadcast_5008315"
      },
      {
        "link_thumb": "https://live.staticflickr.com/65535/51809430468_994f4c743c_n.jpg",
        "link_img": "https://live.staticflickr.com/65535/51809430468_86512fce1d_o.png",
        "id_image": "broadcast_6315596"
      },
      {
        "link_thumb": "https://live.staticflickr.com/65535/51809670414_6505bc42c7_n.jpg",
        "link_img": "https://live.staticflickr.com/65535/51809670414_39e99f0a1d_o.png",
        "id_image": "broadcast_650949"
      }
    ],
    "hash_code_list_img": "474073209"
  },
  {
    "link_it": "https://github.com/lmbstudiocontact/lv_img_3500_it_1/raw/main/draft_lv_img_3500_it.json",
    "id_item": "draft_lv_img_3500_it",
    "id_album": "570943488",
    "english": "draft",
    "list_mean": [
      "cặn",
      "nước vo gạo, nước rửa bát (để nấu cho lợn...)",
      "bã lúa mạch (sau khi ủ bia)",
      "bản phác thảo, bản phác hoạ, đồ án, sơ đồ thiết kế; bản dự thảo một đạo luật...)",
      "(từ Mỹ,nghĩa Mỹ), (quân sự) chế độ quân dịch",
      "(thương nghiệp) sự lấy ra, sự rút (tiền...) ra (bằng ngân phiếu...)",
      "(thương nghiệp) hối phiếu",
      "(quân sự) phân đội, biệt phái, phân đội tăng cường",
      "(kỹ thuật) gió lò",
      "sự kéo",
      "(kiến trúc) sự vạch cỡ; cỡ vạch (dọc theo bờ đá để xây gờ...)",
      "phác thảo, phác hoạ; dự thảo (một đạo luật...)",
      "(từ Mỹ,nghĩa Mỹ), (quân sự) bắt quân dịch, thực hiện chế độ quân dịch đối với",
      "(quân sự) lấy ra, rút ra (một phân đội... để làm công tác biệt phái...)",
      "(kiến trúc) vạch cỡ (bờ đá, để xây gờ...)"
    ],
    "cau_en": "to make a draft on ...",
    "cau_vn": "lấy ra, rút ra (tiền...); (nghĩa bóng) nhờ vào, cậy vào, kêu gọi (tình bạn, lòng đại lượng của ai...)",
    "hash_code_list_mean": "-1960530825",
    "list_img": [
      {
        "link_thumb": "https://live.staticflickr.com/65535/51809662569_8494aaa793_n.jpg",
        "link_img": "https://live.staticflickr.com/65535/51809662569_3e4c52752e_o.png",
        "id_image": "draft_1289255"
      },
      {
        "link_thumb": "https://live.staticflickr.com/65535/51810044225_a4673302a7_n.jpg",
        "link_img": "https://live.staticflickr.com/65535/51810044225_07569e8d72_o.png",
        "id_image": "draft_1289256"
      },
      {
        "link_thumb": "https://live.staticflickr.com/65535/51809307246_ebe491027b_n.jpg",
        "link_img": "https://live.staticflickr.com/65535/51809307246_24d9e0b8a0_o.png",
        "id_image": "draft_3884716"
      },
      {
        "link_thumb": "https://live.staticflickr.com/65535/51809422338_05f92cf184_n.jpg",
        "link_img": "https://live.staticflickr.com/65535/51809422338_14579371a8_o.png",
        "id_image": "draft_4208388"
      },
      {
        "link_thumb": "https://live.staticflickr.com/65535/51809662474_ba97666f56_n.jpg",
        "link_img": "https://live.staticflickr.com/65535/51809662474_e03ea47534_o.png",
        "id_image": "draft_4595100"
      }
    ],
    "hash_code_list_img": "-588368407"
  },
  {
    "link_it": "https://github.com/lmbstudiocontact/lv_img_3500_it_1/raw/main/highland_lv_img_3500_it.json",
    "id_item": "highland_lv_img_3500_it",
    "id_album": "570943488",
    "english": "highland",
    "list_mean": [
      "phần núi non của một nước",
      "( the Highlands ) vùng cao nguyên của xứ Xcốtlen",
      "thuộc về hoặc ở trong vùng núi, vùng cao",
      "( Highland ) thuộc về hoặc ở vùngcao nguyên xứ Xcốtlen"
    ],
    "cau_en": "Highland cattle",
    "cau_vn": "gia súc vùng cao nguyên Xcốtlen",
    "hash_code_list_mean": "2083067922",
    "list_img": [
      {
        "link_thumb": "https://live.staticflickr.com/65535/51810074470_dc45560344_n.jpg",
        "link_img": "https://live.staticflickr.com/65535/51810074470_d307fe9c21_o.png",
        "id_image": "highland_5293869"
      }
    ],
    "hash_code_list_img": "1725382220"
  },
  {
    "link_it": "https://github.com/lmbstudiocontact/lv_img_3500_it_1/raw/main/huge_lv_img_3500_it.json",
    "id_item": "huge_lv_img_3500_it",
    "id_album": "570943488",
    "english": "huge",
    "list_mean": [
      "to lớn, đồ sộ, khổng lồ"
    ],
    "cau_en": "a huge mistake",
    "cau_vn": "sai lầm to lớn",
    "hash_code_list_mean": "-8407041",
    "list_img": [
      {
        "link_thumb": "https://live.staticflickr.com/65535/51809443378_87c68091d9_n.jpg",
        "link_img": "https://live.staticflickr.com/65535/51809443378_bf8e4fa5bb_o.png",
        "id_image": "huge_2904990"
      }
    ],
    "hash_code_list_img": "607370483"
  },
  {
    "link_it": "https://github.com/lmbstudiocontact/lv_img_3500_it_3/raw/main/seesaw_lv_img_3500_it.json",
    "id_item": "seesaw_lv_img_3500_it",
    "id_album": "570943488",
    "english": "seesaw",
    "list_mean": [
      "ván bập bênh (trò chơi của trẻ em)",
      "trò chơi bập bênh",
      "sự chuyển động lên xuống, sự chuyển động qua lại; động tác đẩy tới kéo lui, động tác kéo cưa, tình trạng cò cưa",
      "đẩy tới, kéo lui, cò cưa",
      "chơi bập bênh",
      "chuyển động lên xuống, chuyển động qua lại",
      "(nghĩa bóng) dao động, lưỡng lự, không kiên định"
    ],
    "cau_en": "the slow seesaw of the branch in the wind",
    "cau_vn": "sự lay động khẽ khàng của cành lá trong cơn gió",
    "hash_code_list_mean": "-869499469",
    "list_img": [
      {
        "link_thumb": "https://live.staticflickr.com/65535/51809323101_3c1227a0e1_n.jpg",
        "link_img": "https://live.staticflickr.com/65535/51809323101_13428e4bc9_o.png",
        "id_image": "seesaw_1138467"
      },
      {
        "link_thumb": "https://live.staticflickr.com/65535/51808367972_b75879dc5e_n.jpg",
        "link_img": "https://live.staticflickr.com/65535/51808367972_ba614f5f87_o.png",
        "id_image": "seesaw_1588849"
      },
      {
        "link_thumb": "https://live.staticflickr.com/65535/51809323081_3502d03dfe_n.jpg",
        "link_img": "https://live.staticflickr.com/65535/51809323081_0f87751d73_o.png",
        "id_image": "seesaw_1787539"
      }
    ],
    "hash_code_list_img": "2023027800"
  },
  {
    "link_it": "https://github.com/lmbstudiocontact/lv_img_3500_it_0/raw/main/attribution_lv_img_3500_it.json",
    "id_item": "attribution_lv_img_3500_it",
    "id_album": "570943488",
    "english": "attribution",
    "list_mean": [
      "sự quy kết",
      "quyền hạn được giao, thẩm quyền"
    ],
    "cau_en": "functions and attributions of the administrative tribunal",
    "cau_vn": "chức năng và quyền hạn của toà án hành chính",
    "hash_code_list_mean": "-728789276",
    "list_img": [
      {
        "link_thumb": "https://live.staticflickr.com/65535/51810064480_2b1a2142a1_n.jpg",
        "link_img": "https://live.staticflickr.com/65535/51810064480_9ae8a33029_o.png",
        "id_image": "attribution_2450847"
      }
    ],
    "hash_code_list_img": "1675887015"
  },
  {
    "link_it": "https://github.com/lmbstudiocontact/lv_img_3500_it_1/raw/main/distillation_lv_img_3500_it.json",
    "id_item": "distillation_lv_img_3500_it",
    "id_album": "570943488",
    "english": "distillation",
    "list_mean": [
      "(hoá học) sự chưng cất",
      "sản phẩm cất"
    ],
    "cau_en": "fractional distillation",
    "cau_vn": "sự cất phân đoạn",
    "hash_code_list_mean": "1261907766",
    "list_img": [
      {
        "link_thumb": "https://live.staticflickr.com/65535/51809314641_4ef5f50df2_n.jpg",
        "link_img": "https://live.staticflickr.com/65535/51809314641_81a2aed4fe_o.png",
        "id_image": "distillation_1484382"
      },
      {
        "link_thumb": "https://live.staticflickr.com/65535/51808358722_5e0c094521_n.jpg",
        "link_img": "https://live.staticflickr.com/65535/51808358722_785da4363d_o.png",
        "id_image": "distillation_1486190"
      },
      {
        "link_thumb": "https://live.staticflickr.com/65535/51809669239_c7eb0e86cf_n.jpg",
        "link_img": "https://live.staticflickr.com/65535/51809669239_896157ccc4_o.png",
        "id_image": "distillation_2933815"
      },
      {
        "link_thumb": "https://live.staticflickr.com/65535/51809429423_b74af84c77_n.jpg",
        "link_img": "https://live.staticflickr.com/65535/51809429423_40bbb813de_o.png",
        "id_image": "distillation_3977864"
      },
      {
        "link_thumb": "https://live.staticflickr.com/65535/51809429398_15a5eae92b_n.jpg",
        "link_img": "https://live.staticflickr.com/65535/51809429398_83e913a0d9_o.png",
        "id_image": "distillation_6315393"
      }
    ],
    "hash_code_list_img": "-1787677809"
  },
  {
    "link_it": "https://github.com/lmbstudiocontact/lv_img_3500_it_2/raw/main/outcome_lv_img_3500_it.json",
    "id_item": "outcome_lv_img_3500_it",
    "id_album": "570943488",
    "english": "outcome",
    "list_mean": [
      "hậu quả; kết quả, tác động",
      "(từ Mỹ,nghĩa Mỹ) kết luận lôgic (sau khi suy nghĩ)"
    ],
    "cau_en": "what was the outcome of your meeting ?",
    "cau_vn": "kết quả cuộc họp của các anh như thế nào?",
    "hash_code_list_mean": "1270716906",
    "list_img": [
      {
        "link_thumb": "https://live.staticflickr.com/65535/51809341926_a8ef27f0e8_n.jpg",
        "link_img": "https://live.staticflickr.com/65535/51809341926_aabc5b54af_o.png",
        "id_image": "outcome_1547383"
      }
    ],
    "hash_code_list_img": "1066504783"
  },
  {
    "link_it": "https://github.com/lmbstudiocontact/lv_img_3500_it_0/raw/main/androgynous_lv_img_3500_it.json",
    "id_item": "androgynous_lv_img_3500_it",
    "id_album": "570943488",
    "english": "androgynous",
    "list_mean": [
      "có những đặc tính của cả nam lẫn nữ; lưỡng tính; ái nam ái nữ",
      "(thực vật học) (nói về cây) có cả nhị lẫn nhụy trong cùng một bông hoa; lưỡng tính"
    ],
    "cau_en": "pop-stars dressing up in androgynous styles",
    "cau_vn": "các ngôi sao nhạc pop diện quần áo kiểu ái nam ái nữ",
    "hash_code_list_mean": "-618489494",
    "list_img": [
      {
        "link_thumb": "https://live.staticflickr.com/65535/51809312751_c389f2a344_n.jpg",
        "link_img": "https://live.staticflickr.com/65535/51809312751_72070609b9_o.png",
        "id_image": "androgynous_2534560"
      },
      {
        "link_thumb": "https://live.staticflickr.com/65535/51810049300_1a0d9c83a3_n.jpg",
        "link_img": "https://live.staticflickr.com/65535/51810049300_e802188d93_o.png",
        "id_image": "androgynous_4177097"
      }
    ],
    "hash_code_list_img": "-226646172"
  }
]